[{"id":"c33c8500.a17988","type":"inject","z":"4bf1080e.71c7b8","name":"Show Map in Dashboard","topic":"","payload":"","payloadType":"date","repeat":"","crontab":"","once":true,"onceDelay":"1","x":250,"y":760,"wires":[["d9386d17.eed39"]]},{"id":"d9386d17.eed39","type":"ip","z":"4bf1080e.71c7b8","name":"Get IP","https":false,"timeout":"5000","internalIPv4":true,"internalIPv6":false,"publicIPv4":false,"publicIPv6":false,"x":450,"y":760,"wires":[["9cdac1a8.67c4b"]]},{"id":"9cdac1a8.67c4b","type":"function","z":"4bf1080e.71c7b8","name":"Create LiveFeed-address","func":"msg.payload = \"http://\"+msg.payload.internalIPv4+\":1880/worldmap\";\nreturn msg;","outputs":1,"noerr":0,"x":670,"y":760,"wires":[["91e0c75d.fd1f48"]]},{"id":"91e0c75d.fd1f48","type":"ui_template","z":"4bf1080e.71c7b8","group":"2d868c52.47ad04","name":"Show Map","order":1,"width":"16","height":"12","format":"<div style=\"text-align: center;padding: 0px;\"><iframe id=\"map\" src=\"\" style=\"display: block; width: 100%; height: 75vh; border: none;\" scrolling=\"no\" frameborder=\"0\"></iframe></div>\n<script>\n(function(scope) {\n    // watch msg object from Node-RED\n    scope.$watch('msg', function(msg) {\n        // new message received\n        var x = document.getElementById('map');\n        x.setAttribute('src', msg.payload); \n        });\n})(scope);\n</script>","storeOutMessages":false,"fwdInMessages":true,"templateScope":"local","x":930,"y":760,"wires":[[]]},{"id":"2d868c52.47ad04","type":"ui_group","z":"","name":"Worldmap","tab":"9e54c418.2d3c68","order":1,"disp":true,"width":"16","collapse":false},{"id":"9e54c418.2d3c68","type":"ui_tab","z":"","name":"Pixhawk","icon":"dashboard","disabled":false,"hidden":false}]